
  {
    "id": "LightSensor1",
    "type": "LIGHT",
    "value": 400,
    "timestamp": 1677162146
  }
  {
    "id": "CO2Sensor1",
    "type": "CO2",
    "value": 1000,
    "timestamp": 1677162146
  }
  {
    "id": "CO2Sensor2",
    "type": "CO2",
    "value": 1000,
    "timestamp": 1677162146
  }
  {
    "id": "TempSensor1",
    "type": "TEMPERATURE",
    "value": 19,
    "timestamp": 1677162147
  }
  {
    "id": "LightSensor2",
    "type": "LIGHT",
    "value": 380,
    "timestamp": 1677162148
  }
  {
    "id": "TempSensor3",
    "type": "TEMPERATURE",
    "value": -18,
    "timestamp": 1677162149
  }
  {
    "id": "HumSensor6",
    "type": "HUMIDITY",
    "value": 5,
    "timestamp": 1677162150
  }
  {
    "id": "TempSensor2",
    "type": "TEMPERATURE",
    "value": 18,
    "timestamp": 1677162151
  }
  {
    "id": "TempSensor1",
    "type": "TEMPERATURE",
    "value": 21,
    "timestamp": 1677162152
  }
  {
    "id": "LightSensor4",
    "type": "LIGHT",
    "value": 0,
    "timestamp": 1677162153
  }
  {
    "id": "CO2Sensor3",
    "type": "CO2",
    "value": 1200,
    "timestamp": 1677162154
  }
  {
    "id": "TempSensor4",
    "type": "TEMPERATURE",
    "value": 18,
    "timestamp": 1677162161
  }
  {
    "id": "TempSensor2",
    "type": "TEMPERATURE",
    "value": 20,
    "timestamp": 1677162162
  }
  {
    "id": "LightSensor3",
    "type": "LIGHT",
    "value": 0,
    "timestamp": 1677162162
  }
  {
    "id": "HumSensor1",
    "type": "HUMIDITY",
    "value": 0,
    "timestamp": 1677162162
  }
  {
    "id": "TempSensor1",
    "type": "TEMPERATURE",
    "value": 19,
    "timestamp": 1677162163
  }
  {
    "id": "TempSensor2",
    "type": "TEMPERATURE",
    "value": 18,
    "timestamp": 1677162164
  }
  {
    "id": "CO2Sensor4",
    "type": "CO2",
    "value": 1500,
    "timestamp": 1677162165
  }
  {
    "id": "LightSensor8",
    "type": "LIGHT",
    "value": 0,
    "timestamp": 1677162165
  }
  {
    "id": "TempSensor1",
    "type": "TEMPERATURE",
    "value": 25,
    "timestamp": 1677162166
  }
  {
    "id": "HumSensor8",
    "type": "HUMIDITY",
    "value": 0,
    "timestamp": 1677162167
  }
  {
    "id": "TempSensor5",
    "type": "TEMPERATURE",
    "value": 18,
    "timestamp": 1677162168
  }
  {
    "id": "LightSensor7",
    "type": "LIGHT",
    "value": 100,
    "timestamp": 1677162169
  }
  {
    "id": "TempSensor2",
    "type": "TEMPERATURE",
    "value": 18,
    "timestamp": 1677162170
  }
  {
    "id": "TempSensor3",
    "type": "TEMPERATURE",
    "value": -20,
    "timestamp": 1677162171
  }
  {
    "id": "TempSensor1",
    "type": "TEMPERATURE",
    "value": 60,
    "timestamp": 1677162172
  }
  {
    "id": "LightSensor4",
    "type": "LIGHT",
    "value": 100,
    "timestamp": 1677162173
  }
  {
    "id": "HumSensor3",
    "type": "HUMIDITY",
    "value": 0,
    "timestamp": 1677162174
  }
  {
    "id": "TempSensor2",
    "type": "TEMPERATURE",
    "value": 35,
    "timestamp": 1677162175
  }
  {
    "id": "LightSensor6",
    "type": "LIGHT",
    "value": 100,
    "timestamp": 1677162176
  }
  {
    "id": "TempSensor6",
    "type": "TEMPERATURE",
    "value": 18,
    "timestamp": 1677162177
  }
  {
    "id": "CO2Sensor5",
    "type": "CO2",
    "value": 1200,
    "timestamp": 1677162178
  }
  {
    "id": "CO2Sensor6",
    "type": "CO2",
    "value": 1000,
    "timestamp": 1677162179
  }
  {
    "id": "HumSensor2",
    "type": "HUMIDITY",
    "value": 0,
    "timestamp": 1677162180
  }
  {
    "id": "LightSensor9",
    "type": "LIGHT",
    "value": 0,
    "timestamp": 1677162181
  }
  {
    "id": "TempSensor1",
    "type": "TEMPERATURE",
    "value": 200,
    "timestamp": 1677162188
  }
  {
    "id": "TempSensor2",
    "type": "TEMPERATURE",
    "value": 100,
    "timestamp": 1677162189
  }
  {
    "id": "TempSensor3",
    "type": "TEMPERATURE",
    "value": -19,
    "timestamp": 1677162190
  }
  {
    "id": "CO2Sensor7",
    "type": "CO2",
    "value": 1000,
    "timestamp": 1677162191
  }
  {
    "id": "LightSensor2",
    "type": "LIGHT",
    "value": 5,
    "timestamp": 1677162192
  }
  {
    "id": "HumSensor7",
    "type": "HUMIDITY",
    "value": 0,
    "timestamp": 1677162193
  }
  {
    "id": "CO2Sensor1",
    "type": "CO2",
    "value": 5500,
    "timestamp": 1677162198
  }
  {
    "id": "LightSensor1",
    "type": "LIGHT",
    "value": 10,
    "timestamp": 1677162199
  }
  {
    "id": "CO2Sensor2",
    "type": "CO2",
    "value": 4000,
    "timestamp": 1677162200
  }
  {
    "id": "HumSensor4",
    "type": "HUMIDITY",
    "value": 0,
    "timestamp": 1677162201
  }
  {
    "id": "LightSensor5",
    "type": "LIGHT",
    "value": 100,
    "timestamp": 1677162202
  }
  {
    "id": "HumSensor5",
    "type": "HUMIDITY",
    "value": 0,
    "timestamp": 1677162203
  }
  {
    "id": "HumSensor9",
    "type": "HUMIDITY",
    "value": 0,
    "timestamp": 1677162204
  }
  {
    "id": "LightSensor4",
    "type": "LIGHT",
    "value": 0,
    "timestamp": 1677162205
  }